qadence/__init__.py
qadence/backend.py
qadence/circuit.py
qadence/decompose.py
qadence/divergences.py
qadence/execution.py
qadence/extensions.py
qadence/libs.py
qadence/log_config.yaml
qadence/logger.py
qadence/model.py
qadence/overlap.py
qadence/parameters.py
qadence/pasqal_cloud_connection.py
qadence/protocols.py
qadence/py.typed
qadence/qubit_support.py
qadence/register.py
qadence/serial_expr_grammar.peg
qadence/serialization.py
qadence/states.py
qadence/types.py
qadence/utils.py
qadence/analog/__init__.py
qadence/analog/addressing.py
qadence/analog/constants.py
qadence/analog/device.py
qadence/analog/hamiltonian_terms.py
qadence/analog/parse_analog.py
qadence/backends/__init__.py
qadence/backends/agpsr_utils.py
qadence/backends/api.py
qadence/backends/jax_utils.py
qadence/backends/parameter_shift_rules.py
qadence/backends/utils.py
qadence/backends/horqrux/__init__.py
qadence/backends/horqrux/backend.py
qadence/backends/horqrux/config.py
qadence/backends/horqrux/convert_ops.py
qadence/backends/pulser/__init__.py
qadence/backends/pulser/backend.py
qadence/backends/pulser/channels.py
qadence/backends/pulser/cloud.py
qadence/backends/pulser/config.py
qadence/backends/pulser/convert_ops.py
qadence/backends/pulser/devices.py
qadence/backends/pulser/pulses.py
qadence/backends/pulser/waveforms.py
qadence/backends/pyqtorch/__init__.py
qadence/backends/pyqtorch/backend.py
qadence/backends/pyqtorch/config.py
qadence/backends/pyqtorch/convert_ops.py
qadence/blocks/__init__.py
qadence/blocks/abstract.py
qadence/blocks/analog.py
qadence/blocks/block_to_tensor.py
qadence/blocks/composite.py
qadence/blocks/embedding.py
qadence/blocks/manipulate.py
qadence/blocks/matrix.py
qadence/blocks/primitive.py
qadence/blocks/utils.py
qadence/constructors/__init__.py
qadence/constructors/ala.py
qadence/constructors/feature_maps.py
qadence/constructors/hamiltonians.py
qadence/constructors/hea.py
qadence/constructors/iia.py
qadence/constructors/qft.py
qadence-1.11.5.dist-info/METADATA
qadence-1.11.5.dist-info/WHEEL
qadence-1.11.5.dist-info/licenses/LICENSE
qadence-1.11.5.dist-info/RECORD
