Metadata-Version: 2.4
Name: qadence
Version: 1.11.5
Summary: Pasqal interface for circuit-based quantum computing SDKs
Author-email: Aleksander Wennersteen <aleksander.wennersteen@pasqal.com>, Gert-Jan Both <gert-jan.both@pasqal.com>, Niklas Heim <niklas.heim@pasqal.com>, Mario Dagrada <mario.dagrada@pasqal.com>, Vincent Elfving <vincent.elfving@pasqal.com>, Dominik Seitz <dominik.seitz@pasqal.com>, Roland Guichard <roland.guichard@pasqal.com>, "Joao P. Moutinho" <joao.moutinho@pasqal.com>, Vytautas Abramavicius <vytautas.abramavicius@pasqal.com>, Gergana Velikova <gergana.velikova@pasqal.com>, Eduardo Maschio <
License: PASQAL OPEN-SOURCE SOFTWARE LICENSE (MIT-derived)
License-File: LICENSE
Classifier: License :: Other/Proprietary License
Classifier: Programming Language :: Python
Classifier: Programming Language :: Python :: 3
Classifier: Programming Language :: Python :: 3.9
Classifier: Programming Language :: Python :: 3.10
Classifier: Programming Language :: Python :: 3.11
Classifier: Programming Language :: Python :: 3.12
Classifier: Programming Language :: Python :: 3.13
Classifier: Programming Language :: Python :: Implementation :: CPython
Classifier: Programming Language :: Python :: Implementation :: PyPy
Requires-Python: >=3.9
Requires-Dist: arpeggio==2.0.2
Requires-Dist: deepdiff
Requires-Dist: jsonschema
Requires-Dist: matplotlib
Requires-Dist: nevergrad
Requires-Dist: numpy
Requires-Dist: openfermion
Requires-Dist: pasqal-cloud
Requires-Dist: pyqtorch==1.7.7
Requires-Dist: pyyaml
Requires-Dist: rich
Requires-Dist: scipy
Requires-Dist: sympy<1.13.4
Requires-Dist: sympytorch>=0.1.2
Requires-Dist: tensorboard>=2.12.0
Requires-Dist: torch
Provides-Extra: all
Requires-Dist: libs; extra == 'all'
Requires-Dist: mlflow; extra == 'all'
Requires-Dist: protocols; extra == 'all'
Requires-Dist: pulser; extra == 'all'
Requires-Dist: visualization; extra == 'all'
Provides-Extra: dlprof
Requires-Dist: nvidia-dlprof[pytorch]; extra == 'dlprof'
Requires-Dist: nvidia-pyindex; extra == 'dlprof'
Provides-Extra: horqrux
Requires-Dist: einops; extra == 'horqrux'
Requires-Dist: flax; extra == 'horqrux'
Requires-Dist: horqrux==0.9.0; extra == 'horqrux'
Requires-Dist: jax; extra == 'horqrux'
Requires-Dist: jaxopt; extra == 'horqrux'
Requires-Dist: optax; extra == 'horqrux'
Requires-Dist: sympy2jax; extra == 'horqrux'
Provides-Extra: hub
Requires-Dist: qadence-measurement; extra == 'hub'
Requires-Dist: qadence-mitigation; extra == 'hub'
Requires-Dist: qadence-model; extra == 'hub'
Provides-Extra: libs
Requires-Dist: qadence-libs; extra == 'libs'
Provides-Extra: measurement
Requires-Dist: qadence-measurement; extra == 'measurement'
Provides-Extra: mitigation
Requires-Dist: qadence-mitigation; extra == 'mitigation'
Provides-Extra: mlflow
Requires-Dist: mlflow; extra == 'mlflow'
Provides-Extra: model
Requires-Dist: qadence-model; extra == 'model'
Provides-Extra: protocols
Requires-Dist: qadence-protocols; extra == 'protocols'
Provides-Extra: pulser
Requires-Dist: pasqal-cloud==0.20.2; extra == 'pulser'
Requires-Dist: pulser-core==1.4.0; extra == 'pulser'
Requires-Dist: pulser-simulation==1.4.0; extra == 'pulser'
Provides-Extra: visualization
Requires-Dist: graphviz; extra == 'visualization'
